dino_game/__init__.py
dino_game/game.py
dino_jumper-0.2.0.dist-info/METADATA
dino_jumper-0.2.0.dist-info/WHEEL
dino_jumper-0.2.0.dist-info/entry_points.txt
dino_jumper-0.2.0.dist-info/top_level.txt
dino_jumper-0.2.0.dist-info/RECORD
