Metadata-Version: 2.4
Name: dino-jumper
Version: 0.2.0
Summary: 一个简单的恐龙跳跃游戏
Author-email: Zim mu <sufer76980@163.com>
License: MIT
Classifier: Programming Language :: Python :: 3
Classifier: License :: OSI Approved :: MIT License
Classifier: Operating System :: OS Independent
Requires-Python: >=3.6
Requires-Dist: pygame>=2.0.0
